covjson/__init__.py
covjson/covjson.py
covjson-0.1.4.dist-info/LICENSE
covjson-0.1.4.dist-info/METADATA
covjson-0.1.4.dist-info/WHEEL
covjson-0.1.4.dist-info/entry_points.txt
covjson-0.1.4.dist-info/top_level.txt
covjson-0.1.4.dist-info/RECORD
