Metadata-Version: 2.1
Name: covjson
Version: 0.1.4
Summary: json转换程序
Home-page: https://github.com/pypa/sampleproject
Author: zhaogl1991
Author-email: zhaoguoliang.1991@bytedance.com
License: UNKNOWN
Project-URL: Bug Tracker, https://github.com/pypa/sampleproject/issues
Platform: UNKNOWN
Classifier: Programming Language :: Python :: 3
Classifier: License :: OSI Approved :: MIT License
Classifier: Operating System :: OS Independent
Requires-Python: >=3.6
License-File: LICENSE
